ygrempkg/__init__.py
ygrempkg/ygrempkg.py
ygrempkg-0.0.1.dist-info/LICENSE
ygrempkg-0.0.1.dist-info/METADATA
ygrempkg-0.0.1.dist-info/WHEEL
ygrempkg-0.0.1.dist-info/top_level.txt
ygrempkg-0.0.1.dist-info/RECORD
